isoelectric/__init__.py
isoelectric/ipc.py
isoelectric-1.0.dist-info/METADATA
isoelectric-1.0.dist-info/RECORD
isoelectric-1.0.dist-info/WHEEL
isoelectric-1.0.dist-info/top_level.txt
