Metadata-Version: 2.1
Name: isoelectric
Version: 1.0
Summary: IPC (Isoelectric Point Calculator) - prediction of isoelectric point of proteins and peptides
Home-page: http://isoelectric.org
Author: Lukasz Pawel Kozlowski
Author-email: lukasz.kozlowski.lpk@gmail.com
License: UNKNOWN
Keywords: protein,peptide,isoelectric point,pI,biochemistry,proteomics
Platform: UNKNOWN
Classifier: Programming Language :: Python :: 3
Classifier: License :: Public Domain
Classifier: Operating System :: OS Independent
Requires-Python: >=3.0
